[
    {
        "fields": {
            "name": "UAE dirham",
            "priority": 3,
            "rate": 3.67286,
            "symbol": ""
        },
        "model": "currency.currency",
        "pk": "AED"
    },
    {
        "fields": {
            "name": "Argentine peso",
            "priority": 3,
            "rate": 6.2976049999999999,
            "symbol": "$"
        },
        "model": "currency.currency",
        "pk": "ARS"
    },
    {
        "fields": {
            "name": "Australian dollar",
            "priority": 2,
            "rate": 1.1177619999999999,
            "symbol": "$"
        },
        "model": "currency.currency",
        "pk": "AUD"
    },
    {
        "fields": {
            "name": "Brazilian real",
            "priority": 3,
            "rate": 2.322044,
            "symbol": "R$"
        },
        "model": "currency.currency",
        "pk": "BRL"
    },
    {
        "fields": {
            "name": "Bitcoin",
            "priority": 3,
            "rate": 0.0012714530999999999,
            "symbol": "\u0243"
        },
        "model": "currency.currency",
        "pk": "BTC"
    },
    {
        "fields": {
            "name": "Canadian dollar",
            "priority": 2,
            "rate": 1.0588979999999999,
            "symbol": "$"
        },
        "model": "currency.currency",
        "pk": "CAD"
    },
    {
        "fields": {
            "name": "Swiss franc",
            "priority": 2,
            "rate": 0.88778400000000002,
            "symbol": "CHF"
        },
        "model": "currency.currency",
        "pk": "CHF"
    },
    {
        "fields": {
            "name": "Chilean peso",
            "priority": 3,
            "rate": 528.25399800000002,
            "symbol": "$"
        },
        "model": "currency.currency",
        "pk": "CLP"
    },
    {
        "fields": {
            "name": "Chinese yuan renminbi",
            "priority": 3,
            "rate": 6.0804039999999997,
            "symbol": "\u00a5"
        },
        "model": "currency.currency",
        "pk": "CNY"
    },
    {
        "fields": {
            "name": "Colombian peso",
            "priority": 3,
            "rate": 1933.8833500000001,
            "symbol": "$"
        },
        "model": "currency.currency",
        "pk": "COP"
    },
    {
        "fields": {
            "name": "Czech koruna",
            "priority": 3,
            "rate": 20.04392,
            "symbol": "K\u010d"
        },
        "model": "currency.currency",
        "pk": "CZK"
    },
    {
        "fields": {
            "name": "Danish krone",
            "priority": 3,
            "rate": 5.4222390000000003,
            "symbol": "kr"
        },
        "model": "currency.currency",
        "pk": "DKK"
    },
    {
        "fields": {
            "name": "Algerian dinar",
            "priority": 3,
            "rate": 78.255739000000005,
            "symbol": "\u062f\u062c"
        },
        "model": "currency.currency",
        "pk": "DZD"
    },
    {
        "fields": {
            "name": "Egyptian pound",
            "priority": 3,
            "rate": 6.885345,
            "symbol": "\u00a3"
        },
        "model": "currency.currency",
        "pk": "EGP"
    },
    {
        "fields": {
            "name": "EU euro",
            "priority": 1,
            "rate": 0.72646599999999995,
            "symbol": "\u20ac"
        },
        "model": "currency.currency",
        "pk": "EUR"
    },
    {
        "fields": {
            "name": "British pound",
            "priority": 1,
            "rate": 0.61326499999999995,
            "symbol": "\u00a3"
        },
        "model": "currency.currency",
        "pk": "GBP"
    },
    {
        "fields": {
            "name": "Hong Kong SAR dollar",
            "priority": 2,
            "rate": 7.7534020000000003,
            "symbol": "$"
        },
        "model": "currency.currency",
        "pk": "HKD"
    },
    {
        "fields": {
            "name": "Indonesian rupiah",
            "priority": 3,
            "rate": 12076.4,
            "symbol": "Rp"
        },
        "model": "currency.currency",
        "pk": "IDR"
    },
    {
        "fields": {
            "name": "Israeli new shekel",
            "priority": 3,
            "rate": 3.5030739999999998,
            "symbol": "\u20aa"
        },
        "model": "currency.currency",
        "pk": "ILS"
    },
    {
        "fields": {
            "name": "Indian rupee",
            "priority": 2,
            "rate": 61.804960000000001,
            "symbol": "\u20b9"
        },
        "model": "currency.currency",
        "pk": "INR"
    },
    {
        "fields": {
            "name": "Japanese yen",
            "priority": 1,
            "rate": 103.0621,
            "symbol": "\u00a5"
        },
        "model": "currency.currency",
        "pk": "JPY"
    },
    {
        "fields": {
            "name": "South Korean won",
            "priority": 2,
            "rate": 1052.653335,
            "symbol": "\u20a9"
        },
        "model": "currency.currency",
        "pk": "KRW"
    },
    {
        "fields": {
            "name": "Mexican peso",
            "priority": 2,
            "rate": 12.91675,
            "symbol": "$"
        },
        "model": "currency.currency",
        "pk": "MXN"
    },
    {
        "fields": {
            "name": "Malaysian ringgit",
            "priority": 3,
            "rate": 3.2397300000000002,
            "symbol": "RM"
        },
        "model": "currency.currency",
        "pk": "MYR"
    },
    {
        "fields": {
            "name": "Norwegian krone",
            "priority": 2,
            "rate": 6.1508279999999997,
            "symbol": "kr"
        },
        "model": "currency.currency",
        "pk": "NOK"
    },
    {
        "fields": {
            "name": "New Zealand dollar",
            "priority": 2,
            "rate": 1.2094640000000001,
            "symbol": "$"
        },
        "model": "currency.currency",
        "pk": "NZD"
    },
    {
        "fields": {
            "name": "Polish zloty",
            "priority": 3,
            "rate": 3.0349789999999999,
            "symbol": "z\u0142"
        },
        "model": "currency.currency",
        "pk": "PLN"
    },
    {
        "fields": {
            "name": "Russian ruble",
            "priority": 3,
            "rate": 32.896000000000001,
            "symbol": "\u0440\u0443\u0431"
        },
        "model": "currency.currency",
        "pk": "RUB"
    },
    {
        "fields": {
            "name": "Saudi riyal",
            "priority": 3,
            "rate": 3.7504900000000001,
            "symbol": "\ufdfc"
        },
        "model": "currency.currency",
        "pk": "SAR"
    },
    {
        "fields": {
            "name": "Swedish krona",
            "priority": 2,
            "rate": 6.56494,
            "symbol": "kr"
        },
        "model": "currency.currency",
        "pk": "SEK"
    },
    {
        "fields": {
            "name": "Singapore dollar",
            "priority": 2,
            "rate": 1.255671,
            "symbol": "$"
        },
        "model": "currency.currency",
        "pk": "SGD"
    },
    {
        "fields": {
            "name": "Thai baht",
            "priority": 3,
            "rate": 32.035400000000003,
            "symbol": "\u0e3f"
        },
        "model": "currency.currency",
        "pk": "THB"
    },
    {
        "fields": {
            "name": "Turkish lira",
            "priority": 3,
            "rate": 2.0325799999999998,
            "symbol": "\\u20BA"
        },
        "model": "currency.currency",
        "pk": "TRY"
    },
    {
        "fields": {
            "name": "Taiwan New dollar",
            "priority": 3,
            "rate": 29.650580000000001,
            "symbol": "NT$"
        },
        "model": "currency.currency",
        "pk": "TWD"
    },
    {
        "fields": {
            "name": "US dollar",
            "priority": 1,
            "rate": 1.0,
            "symbol": "$"
        },
        "model": "currency.currency",
        "pk": "USD"
    },
    {
        "fields": {
            "name": "Venezuelan bolivar fuerte",
            "priority": 3,
            "rate": 6.2910000000000004,
            "symbol": "Bs"
        },
        "model": "currency.currency",
        "pk": "VEF"
    },
    {
        "fields": {
            "name": "Vietnamese dong",
            "priority": 3,
            "rate": 21094.0,
            "symbol": "\u20ab"
        },
        "model": "currency.currency",
        "pk": "VND"
    },
    {
        "fields": {
            "name": "South African rand",
            "priority": 3,
            "rate": 10.31204,
            "symbol": "R"
        },
        "model": "currency.currency",
        "pk": "ZAR"
    }
]