[{"pk": 1, "model": "core.currency", "fields": {"iso_code": "DZD", "rate": 79.447271, "name": "Algerian dinar"}}, {"pk": 2, "model": "core.currency", "fields": {"iso_code": "NAD", "rate": 9.851101, "name": "Namibian dollar"}}, {"pk": 3, "model": "core.currency", "fields": {"iso_code": "GHS", "rate": 2.085503, "name": "Ghanaian new cedi"}}, {"pk": 4, "model": "core.currency", "fields": {"iso_code": "EGP", "rate": 7.00118, "name": "Egyptian pound"}}, {"pk": 5, "model": "core.currency", "fields": {"iso_code": "BGN", "rate": 1.474021, "name": "Bulgarian lev"}}, {"pk": 6, "model": "core.currency", "fields": {"iso_code": "PAB", "rate": 1, "name": "Panamanian balboa"}}, {"pk": 7, "model": "core.currency", "fields": {"iso_code": "BOB", "rate": 6.910101, "name": "Bolivian boliviano"}}, {"pk": 8, "model": "core.currency", "fields": {"iso_code": "DKK", "rate": 5.615948, "name": "Danish krone"}}, {"pk": 9, "model": "core.currency", "fields": {"iso_code": "BWP", "rate": 8.526347, "name": "Botswana pula"}}, {"pk": 10, "model": "core.currency", "fields": {"iso_code": "LBP", "rate": 1511.532255, "name": "Lebanese pound"}}, {"pk": 11, "model": "core.currency", "fields": {"iso_code": "TZS", "rate": 1620.368885, "name": "Tanzanian shilling"}}, {"pk": 12, "model": "core.currency", "fields": {"iso_code": "VND", "rate": 21163.186425, "name": "Vietnamese dong"}}, {"pk": 13, "model": "core.currency", "fields": {"iso_code": "AOA", "rate": 95.987099, "name": "Angolan kwanza"}}, {"pk": 14, "model": "core.currency", "fields": {"iso_code": "KHR", "rate": 4098.12, "name": "Cambodian riel"}}, {"pk": 15, "model": "core.currency", "fields": {"iso_code": "MYR", "rate": 3.242759, "name": "Malaysian ringgit"}}, {"pk": 16, "model": "core.currency", "fields": {"iso_code": "KYD", "rate": 0.822418, "name": "Cayman Islands dollar"}}, {"pk": 17, "model": "core.currency", "fields": {"iso_code": "LYD", "rate": 1.265973, "name": "Libyan dinar"}}, {"pk": 18, "model": "core.currency", "fields": {"iso_code": "UAH", "rate": 8.122408, "name": "Ukrainian hryvnia"}}, {"pk": 19, "model": "core.currency", "fields": {"iso_code": "JOD", "rate": 0.708305, "name": "Jordanian dinar"}}, {"pk": 20, "model": "core.currency", "fields": {"iso_code": "AWG", "rate": 1.789967, "name": "Aruban guilder"}}, {"pk": 21, "model": "core.currency", "fields": {"iso_code": "SAR", "rate": 3.75051, "name": "Saudi riyal"}}, {"pk": 22, "model": "core.currency", "fields": {"iso_code": "EUR", "rate": 0.753099, "name": "EU euro"}}, {"pk": 23, "model": "core.currency", "fields": {"iso_code": "HKD", "rate": 7.755523, "name": "Hong Kong SAR dollar"}}, {"pk": 24, "model": "core.currency", "fields": {"iso_code": "CHF", "rate": 0.92873, "name": "Swiss franc"}}, {"pk": 25, "model": "core.currency", "fields": {"iso_code": "GIP", "rate": 0.658581, "name": "Gibraltar pound"}}, {"pk": 26, "model": "core.currency", "fields": {"iso_code": "BYR", "rate": 8882.98, "name": "Belarusian ruble"}}, {"pk": 27, "model": "core.currency", "fields": {"iso_code": "ALL", "rate": 105.670001, "name": "Albanian lek"}}, {"pk": 28, "model": "core.currency", "fields": {"iso_code": "MRO", "rate": 301.78125, "name": "Mauritanian ouguiya"}}, {"pk": 29, "model": "core.currency", "fields": {"iso_code": "HRK", "rate": 5.655215, "name": "Croatian kuna"}}, {"pk": 30, "model": "core.currency", "fields": {"iso_code": "DJF", "rate": 177.999999, "name": "Djibouti franc"}}, {"pk": 31, "model": "core.currency", "fields": {"iso_code": "SZL", "rate": 9.846254, "name": "Swaziland lilangeni"}}, {"pk": 32, "model": "core.currency", "fields": {"iso_code": "THB", "rate": 31.329507, "name": "Thai baht"}}, {"pk": 33, "model": "core.currency", "fields": {"iso_code": "XAF", "rate": 494.451825, "name": "CFA franc BEAC"}}, {"pk": 34, "model": "core.currency", "fields": {"iso_code": "BND", "rate": 1.271214, "name": "Brunei dollar"}}, {"pk": 35, "model": "core.currency", "fields": {"iso_code": "ISK", "rate": 119.406249, "name": "Icelandic krona"}}, {"pk": 36, "model": "core.currency", "fields": {"iso_code": "UYU", "rate": 21.308769, "name": "Uruguayan peso uruguayo"}}, {"pk": 37, "model": "core.currency", "fields": {"iso_code": "NIO", "rate": 24.668458, "name": "Nicaraguan cordoba oro"}}, {"pk": 38, "model": "core.currency", "fields": {"iso_code": "LAK", "rate": 7784.661667, "name": "Lao kip"}}, {"pk": 39, "model": "core.currency", "fields": {"iso_code": "SYP", "rate": 70.150014, "name": "Syrian pound"}}, {"pk": 40, "model": "core.currency", "fields": {"iso_code": "MAD", "rate": 8.412525, "name": "Moroccan dirham"}}, {"pk": 41, "model": "core.currency", "fields": {"iso_code": "MZN", "rate": 29.870733, "name": "Mozambique new metical"}}, {"pk": 42, "model": "core.currency", "fields": {"iso_code": "PHP", "rate": 43.484545, "name": "Philippine peso"}}, {"pk": 43, "model": "core.currency", "fields": {"iso_code": "ZAR", "rate": 9.890026, "name": "South African rand"}}, {"pk": 44, "model": "core.currency", "fields": {"iso_code": "NPR", "rate": 97.138158, "name": "Nepalese rupee"}}, {"pk": 45, "model": "core.currency", "fields": {"iso_code": "ZWL", "rate": 322.387247, "name": "Zimbabwe dollar"}}, {"pk": 46, "model": "core.currency", "fields": {"iso_code": "NGN", "rate": 160.637577, "name": "Nigerian naira"}}, {"pk": 47, "model": "core.currency", "fields": {"iso_code": "CRC", "rate": 502.865652, "name": "Costa Rican colon"}}, {"pk": 48, "model": "core.currency", "fields": {"iso_code": "AED", "rate": 3.673053, "name": "UAE dirham"}}, {"pk": 49, "model": "core.currency", "fields": {"iso_code": "EEK", "rate": 11.771245, "name": "Estonian kroon"}}, {"pk": 50, "model": "core.currency", "fields": {"iso_code": "MWK", "rate": 327.78775, "name": "Malawi kwacha"}}, {"pk": 51, "model": "core.currency", "fields": {"iso_code": "LKR", "rate": 131.666548, "name": "Sri Lanka rupee"}}, {"pk": 52, "model": "core.currency", "fields": {"iso_code": "PKR", "rate": 101.699942, "name": "Pakistani rupee"}}, {"pk": 53, "model": "core.currency", "fields": {"iso_code": "HUF", "rate": 225.82642, "name": "Hungarian forint"}}, {"pk": 54, "model": "core.currency", "fields": {"iso_code": "BMD", "rate": 1, "name": "Bermudian dollar"}}, {"pk": 55, "model": "core.currency", "fields": {"iso_code": "LSL", "rate": 9.847004, "name": "Lesotho loti"}}, {"pk": 56, "model": "core.currency", "fields": {"iso_code": "MNT", "rate": 1486.5, "name": "Mongolian tugrik"}}, {"pk": 57, "model": "core.currency", "fields": {"iso_code": "AMD", "rate": 413.821249, "name": "Armenian dram"}}, {"pk": 58, "model": "core.currency", "fields": {"iso_code": "UGX", "rate": 2586.507333, "name": "Uganda new shilling"}}, {"pk": 59, "model": "core.currency", "fields": {"iso_code": "QAR", "rate": 3.641537, "name": "Qatari rial"}}, {"pk": 60, "model": "core.currency", "fields": {"iso_code": "XDR", "rate": 0.66095, "name": "IMF special drawing right"}}, {"pk": 61, "model": "core.currency", "fields": {"iso_code": "JMD", "rate": 101.312115, "name": "Jamaican dollar"}}, {"pk": 62, "model": "core.currency", "fields": {"iso_code": "GEL", "rate": 1.654475, "name": "Georgian lari"}}, {"pk": 63, "model": "core.currency", "fields": {"iso_code": "SHP", "rate": 0.658581, "name": "Saint Helena pound"}}, {"pk": 64, "model": "core.currency", "fields": {"iso_code": "AFN", "rate": 55.9374, "name": "Afghanistan afghani"}}, {"pk": 65, "model": "core.currency", "fields": {"iso_code": "SBD", "rate": 7.112387, "name": "Solomon Islands dollar"}}, {"pk": 66, "model": "core.currency", "fields": {"iso_code": "KPW", "rate": 900, "name": "North Korean won"}}, {"pk": 67, "model": "core.currency", "fields": {"iso_code": "TRY", "rate": 1.936699, "name": "Turkish lira"}}, {"pk": 68, "model": "core.currency", "fields": {"iso_code": "BDT", "rate": 77.916138, "name": "Bangladeshi taka"}}, {"pk": 69, "model": "core.currency", "fields": {"iso_code": "YER", "rate": 214.985406, "name": "Yemeni rial"}}, {"pk": 70, "model": "core.currency", "fields": {"iso_code": "HTG", "rate": 43.355925, "name": "Haitian gourde"}}, {"pk": 71, "model": "core.currency", "fields": {"iso_code": "XOF", "rate": 494.874503, "name": "CFA franc BCEAO"}}, {"pk": 72, "model": "core.currency", "fields": {"iso_code": "MGA", "rate": 2192.94, "name": "Malagasy ariary"}}, {"pk": 73, "model": "core.currency", "fields": {"iso_code": "ANG", "rate": 1.7849, "name": "Netherlands Antillian guilder"}}, {"pk": 74, "model": "core.currency", "fields": {"iso_code": "LRD", "rate": 75.209099, "name": "Liberian dollar"}}, {"pk": 75, "model": "core.currency", "fields": {"iso_code": "RWF", "rate": 649.75575, "name": "Rwandan franc"}}, {"pk": 76, "model": "core.currency", "fields": {"iso_code": "NOK", "rate": 5.925218, "name": "Norwegian krone"}}, {"pk": 77, "model": "core.currency", "fields": {"iso_code": "MOP", "rate": 7.988253, "name": "Macao SAR pataca"}}, {"pk": 78, "model": "core.currency", "fields": {"iso_code": "INR", "rate": 60.588183, "name": "Indian rupee"}}, {"pk": 79, "model": "core.currency", "fields": {"iso_code": "MXN", "rate": 12.816143, "name": "Mexican peso"}}, {"pk": 80, "model": "core.currency", "fields": {"iso_code": "CZK", "rate": 19.511431, "name": "Czech koruna"}}, {"pk": 81, "model": "core.currency", "fields": {"iso_code": "TJS", "rate": 4.7682, "name": "Tajik somoni"}}, {"pk": 82, "model": "core.currency", "fields": {"iso_code": "BTN", "rate": 60.589817, "name": "Bhutan ngultrum"}}, {"pk": 83, "model": "core.currency", "fields": {"iso_code": "COP", "rate": 1894.714793, "name": "Colombian peso"}}, {"pk": 84, "model": "core.currency", "fields": {"iso_code": "TMT", "rate": 2.85015, "name": "Turkmen new manat"}}, {"pk": 85, "model": "core.currency", "fields": {"iso_code": "MUR", "rate": 30.926663, "name": "Mauritius rupee"}}, {"pk": 86, "model": "core.currency", "fields": {"iso_code": "IDR", "rate": 10288.1446, "name": "Indonesian rupiah"}}, {"pk": 87, "model": "core.currency", "fields": {"iso_code": "HNL", "rate": 20.395631, "name": "Honduran lempira"}}, {"pk": 88, "model": "core.currency", "fields": {"iso_code": "XPF", "rate": 90.299163, "name": "CFP franc"}}, {"pk": 89, "model": "core.currency", "fields": {"iso_code": "FJD", "rate": 1.878978, "name": "Fiji dollar"}}, {"pk": 90, "model": "core.currency", "fields": {"iso_code": "ETB", "rate": 18.800013, "name": "Ethiopian birr"}}, {"pk": 91, "model": "core.currency", "fields": {"iso_code": "PEN", "rate": 2.785446, "name": "Peruvian nuevo sol"}}, {"pk": 92, "model": "core.currency", "fields": {"iso_code": "BZD", "rate": 1.985694, "name": "Belize dollar"}}, {"pk": 93, "model": "core.currency", "fields": {"iso_code": "ILS", "rate": 3.569744, "name": "Israeli new shekel"}}, {"pk": 94, "model": "core.currency", "fields": {"iso_code": "DOP", "rate": 41.896935, "name": "Dominican peso"}}, {"pk": 95, "model": "core.currency", "fields": {"iso_code": "TWD", "rate": 30.013166, "name": "Taiwan New dollar"}}, {"pk": 96, "model": "core.currency", "fields": {"iso_code": "MDL", "rate": 12.129163, "name": "Moldovan leu"}}, {"pk": 97, "model": "core.currency", "fields": {"iso_code": "BSD", "rate": 1, "name": "Bahamian dollar"}}, {"pk": 98, "model": "core.currency", "fields": {"iso_code": "SEK", "rate": 6.540387, "name": "Swedish krona"}}, {"pk": 99, "model": "core.currency", "fields": {"iso_code": "ZMK", "rate": 5227.108333, "name": "Zambian kwacha"}}, {"pk": 100, "model": "core.currency", "fields": {"iso_code": "AUD", "rate": 1.114585, "name": "Australian dollar"}}, {"pk": 101, "model": "core.currency", "fields": {"iso_code": "SRD", "rate": 3.275, "name": "Suriname dollar"}}, {"pk": 102, "model": "core.currency", "fields": {"iso_code": "CUP", "rate": 22.687419, "name": "Cuban peso"}}, {"pk": 103, "model": "core.currency", "fields": {"iso_code": "BBD", "rate": 2, "name": "Barbados dollar"}}, {"pk": 104, "model": "core.currency", "fields": {"iso_code": "KMF", "rate": 371.249863, "name": "Comoros franc"}}, {"pk": 105, "model": "core.currency", "fields": {"iso_code": "KRW", "rate": 1121.288625, "name": "South Korean won"}}, {"pk": 106, "model": "core.currency", "fields": {"iso_code": "GMD", "rate": 32.60115, "name": "Gambian dalasi"}}, {"pk": 107, "model": "core.currency", "fields": {"iso_code": "VEF", "rate": 6.291226, "name": "Venezuelan bolivar fuerte"}}, {"pk": 108, "model": "core.currency", "fields": {"iso_code": "GTQ", "rate": 7.838033, "name": "Guatemalan quetzal"}}, {"pk": 109, "model": "core.currency", "fields": {"iso_code": "CLP", "rate": 515.435209, "name": "Chilean peso"}}, {"pk": 110, "model": "core.currency", "fields": {"iso_code": "LTL", "rate": 2.600869, "name": "Lithuanian litas"}}, {"pk": 111, "model": "core.currency", "fields": {"iso_code": "CDF", "rate": 923.526837, "name": "Congolese franc"}}, {"pk": 112, "model": "core.currency", "fields": {"iso_code": "XCD", "rate": 2.70195, "name": "East Caribbean dollar"}}, {"pk": 113, "model": "core.currency", "fields": {"iso_code": "KZT", "rate": 153.457152, "name": "Kazakh tenge"}}, {"pk": 114, "model": "core.currency", "fields": {"iso_code": "RUB", "rate": 32.992425, "name": "Russian ruble"}}, {"pk": 115, "model": "core.currency", "fields": {"iso_code": "XAG", "rate": 0.050844, "name": "Silver (ounce)"}}, {"pk": 116, "model": "core.currency", "fields": {"iso_code": "TTD", "rate": 6.411145, "name": "Trinidad and Tobago dollar"}}, {"pk": 117, "model": "core.currency", "fields": {"iso_code": "OMR", "rate": 0.385011, "name": "Omani rial"}}, {"pk": 118, "model": "core.currency", "fields": {"iso_code": "BRL", "rate": 2.288142, "name": "Brazilian real"}}, {"pk": 119, "model": "core.currency", "fields": {"iso_code": "MMK", "rate": 975.511125, "name": "Myanmar kyat"}}, {"pk": 120, "model": "core.currency", "fields": {"iso_code": "PLN", "rate": 3.196823, "name": "Polish zloty"}}, {"pk": 121, "model": "core.currency", "fields": {"iso_code": "PYG", "rate": 4428.78469, "name": "Paraguayan guarani"}}, {"pk": 122, "model": "core.currency", "fields": {"iso_code": "KES", "rate": 87.358101, "name": "Kenyan shilling"}}, {"pk": 123, "model": "core.currency", "fields": {"iso_code": "SVC", "rate": 8.74791, "name": "El Salvador colon"}}, {"pk": 124, "model": "core.currency", "fields": {"iso_code": "MKD", "rate": 46.46497, "name": "Macedonian denar"}}, {"pk": 125, "model": "core.currency", "fields": {"iso_code": "GBP", "rate": 0.658581, "name": "British pound"}}, {"pk": 126, "model": "core.currency", "fields": {"iso_code": "AZN", "rate": 0.7844, "name": "Azerbaijanian new manat"}}, {"pk": 127, "model": "core.currency", "fields": {"iso_code": "TOP", "rate": 1.833769, "name": "Tongan pa'anga"}}, {"pk": 128, "model": "core.currency", "fields": {"iso_code": "MVR", "rate": 15.37535, "name": "Maldivian rufiyaa"}}, {"pk": 129, "model": "core.currency", "fields": {"iso_code": "VUV", "rate": 96.2, "name": "Vanuatu vatu"}}, {"pk": 130, "model": "core.currency", "fields": {"iso_code": "GNF", "rate": 7016.035, "name": "Guinean franc"}}, {"pk": 131, "model": "core.currency", "fields": {"iso_code": "WST", "rate": 2.341208, "name": "Samoan tala"}}, {"pk": 132, "model": "core.currency", "fields": {"iso_code": "IQD", "rate": 1164.801667, "name": "Iraqi dinar"}}, {"pk": 133, "model": "core.currency", "fields": {"iso_code": "SCR", "rate": 11.98892, "name": "Seychelles rupee"}}, {"pk": 134, "model": "core.currency", "fields": {"iso_code": "CAD", "rate": 1.028832, "name": "Canadian dollar"}}, {"pk": 135, "model": "core.currency", "fields": {"iso_code": "CVE", "rate": 82.492999, "name": "Cape Verde escudo"}}, {"pk": 136, "model": "core.currency", "fields": {"iso_code": "KWD", "rate": 0.284408, "name": "Kuwaiti dinar"}}, {"pk": 137, "model": "core.currency", "fields": {"iso_code": "BIF", "rate": 1537.985, "name": "Burundi franc"}}, {"pk": 138, "model": "core.currency", "fields": {"iso_code": "PGK", "rate": 2.2863, "name": "Papua New Guinea kina"}}, {"pk": 139, "model": "core.currency", "fields": {"iso_code": "SOS", "rate": 1379.493333, "name": "Somali shilling"}}, {"pk": 140, "model": "core.currency", "fields": {"iso_code": "SGD", "rate": 1.272925, "name": "Singapore dollar"}}, {"pk": 141, "model": "core.currency", "fields": {"iso_code": "UZS", "rate": 2108.020819, "name": "Uzbekistani sum"}}, {"pk": 142, "model": "core.currency", "fields": {"iso_code": "STD", "rate": 18504.283333, "name": "Sao Tome and Principe dobra"}}, {"pk": 143, "model": "core.currency", "fields": {"iso_code": "IRR", "rate": 12239.2238, "name": "Iranian rial"}}, {"pk": 144, "model": "core.currency", "fields": {"iso_code": "CNY", "rate": 6.13932, "name": "Chinese yuan renminbi"}}, {"pk": 145, "model": "core.currency", "fields": {"iso_code": "SLL", "rate": 4323.448277, "name": "Sierra Leone leone"}}, {"pk": 146, "model": "core.currency", "fields": {"iso_code": "TND", "rate": 1.64674, "name": "Tunisian dinar"}}, {"pk": 147, "model": "core.currency", "fields": {"iso_code": "GYD", "rate": 202.081666, "name": "Guyana dollar"}}, {"pk": 148, "model": "core.currency", "fields": {"iso_code": "NZD", "rate": 1.256372, "name": "New Zealand dollar"}}, {"pk": 149, "model": "core.currency", "fields": {"iso_code": "FKP", "rate": 0.658581, "name": "Falkland Islands pound"}}, {"pk": 150, "model": "core.currency", "fields": {"iso_code": "LVL", "rate": 0.52937, "name": "Latvian lats"}}, {"pk": 151, "model": "core.currency", "fields": {"iso_code": "USD", "rate": 1, "name": "US dollar"}}, {"pk": 152, "model": "core.currency", "fields": {"iso_code": "KGS", "rate": 48.864, "name": "Kyrgyz som"}}, {"pk": 153, "model": "core.currency", "fields": {"iso_code": "ARS", "rate": 5.500998, "name": "Argentine peso"}}, {"pk": 154, "model": "core.currency", "fields": {"iso_code": "RON", "rate": 3.321746, "name": "Romanian new leu"}}, {"pk": 155, "model": "core.currency", "fields": {"iso_code": "RSD", "rate": 85.737044, "name": "Serbian dinar"}}, {"pk": 156, "model": "core.currency", "fields": {"iso_code": "BHD", "rate": 0.377043, "name": "Bahraini dinar"}}, {"pk": 157, "model": "core.currency", "fields": {"iso_code": "JPY", "rate": 98.216833, "name": "Japanese yen"}}, {"pk": 158, "model": "core.currency", "fields": {"iso_code": "SDG", "rate": 4.409497, "name": "Sudanese pound"}}, {"pk": 159, "model": "core.currency", "fields": {"iso_code": "XAU", "rate": 0.000765, "name": "Gold (ounce)"}}]